pygrowthstandards/__init__.py
pygrowthstandards/data/__init__.py
pygrowthstandards/data/extract.py
pygrowthstandards/data/load.py
pygrowthstandards/data/main.py
pygrowthstandards/data/pygrowthstandards_1.1.parquet
pygrowthstandards/data/transform.py
pygrowthstandards/functional/__init__.py
pygrowthstandards/functional/calculator.py
pygrowthstandards/functional/data.py
pygrowthstandards/functional/main.py
pygrowthstandards/oop/__init__.py
pygrowthstandards/oop/calculator.py
pygrowthstandards/oop/main.py
pygrowthstandards/oop/measurement.py
pygrowthstandards/oop/patient.py
pygrowthstandards/oop/plotter.py
pygrowthstandards/pdf/convert.py
pygrowthstandards/utils/__init__.py
pygrowthstandards/utils/config.py
pygrowthstandards/utils/constants.py
pygrowthstandards/utils/errors.py
pygrowthstandards/utils/results.py
pygrowthstandards/utils/stats.py
pygrowthstandards/utils/plot/style.py
pygrowthstandards/utils/plot/xticks.py
pygrowthstandards-0.1.2.dist-info/METADATA
pygrowthstandards-0.1.2.dist-info/WHEEL
pygrowthstandards-0.1.2.dist-info/licenses/LICENSE
pygrowthstandards-0.1.2.dist-info/RECORD
