Metadata-Version: 2.4
Name: pygrowthstandards
Version: 0.1.2
Summary: A Python library for calculating child growth z-scores and percentiles using WHO and INTERGROWTH-21st standards
Project-URL: Homepage, https://github.com/Yannngn/pygrowthstandards
Project-URL: Repository, https://github.com/Yannngn/pygrowthstandards
Project-URL: Issues, https://github.com/Yannngn/pygrowthstandards/issues
Project-URL: Documentation, https://github.com/Yannngn/pygrowthstandards#readme
Author-email: Yannngn <contato.yannnob@gmail.com>
Maintainer-email: Yannngn <contato.yannnob@gmail.com>
License: MIT
License-File: LICENSE
Keywords: anthropometry,children,growth,intergrowth,pediatrics,percentile,who,z-score
Classifier: Development Status :: 4 - Beta
Classifier: Intended Audience :: Healthcare Industry
Classifier: Intended Audience :: Science/Research
Classifier: License :: OSI Approved :: MIT License
Classifier: Operating System :: OS Independent
Classifier: Programming Language :: Python :: 3
Classifier: Programming Language :: Python :: 3.11
Classifier: Programming Language :: Python :: 3.12
Classifier: Programming Language :: Python :: 3.13
Classifier: Topic :: Scientific/Engineering :: Information Analysis
Classifier: Topic :: Scientific/Engineering :: Medical Science Apps.
Requires-Python: >=3.11
Requires-Dist: pandas[computation,output-formatting,parquet,performance,plot]>=2.3.0
